echoshader/__init__.py
echoshader/_echoshader_version.py
echoshader/box.py
echoshader/core.py
echoshader/curtain.py
echoshader/echogram.py
echoshader/hist.py
echoshader/map.py
echoshader/utils.py
echoshader/version.py
echoshader/test_data/concatenated_MVBS.nc
echoshader/tests/__init__.py
echoshader/tests/test.py
echoshader/tests/test_plots.py
echoshader-0.1.0.dist-info/LICENSE
echoshader-0.1.0.dist-info/METADATA
echoshader-0.1.0.dist-info/WHEEL
echoshader-0.1.0.dist-info/top_level.txt
echoshader-0.1.0.dist-info/RECORD
