Metadata-Version: 2.1
Name: echoshader
Version: 0.1.0
Summary: Open Source Python package for building ocean sonar data visualizations.
Home-page: https://github.com/OSOceanAcoustics/echoshader
Author: Dingrui Lei
Author-email: leidingrui426@gmail.com
Maintainer: Dingrui Lei
Maintainer-email: leidingrui426@gmail.com
License: MIT
Platform: OS Independent
Classifier: Development Status :: 1 - Planning
Classifier: Environment :: Console
Classifier: Intended Audience :: Science/Research
Classifier: License :: OSI Approved :: MIT License
Classifier: Operating System :: OS Independent
Classifier: Programming Language :: Python
Classifier: Programming Language :: Python :: 3 :: Only
Classifier: Programming Language :: Python :: 3.8
Classifier: Programming Language :: Python :: 3.9
Classifier: Programming Language :: Python :: 3.10
Classifier: Topic :: Scientific/Engineering :: Visualization
Requires-Python: >=3.8
License-File: LICENSE
Requires-Dist: echopype
Requires-Dist: hvplot
Requires-Dist: geoviews
Requires-Dist: pyvista
Requires-Dist: ipykernel
Requires-Dist: pandas <2.0.0
Provides-Extra: all
Requires-Dist: pytest ; extra == 'all'
Requires-Dist: pytest-cov ; extra == 'all'
Requires-Dist: pytest-flake8 ; extra == 'all'
Requires-Dist: pytest-xdist ; extra == 'all'
Requires-Dist: pytest-mock ; extra == 'all'
Requires-Dist: black ; extra == 'all'
Requires-Dist: check-manifest ; extra == 'all'
Requires-Dist: flake8 ; extra == 'all'
Requires-Dist: flake8-builtins ; extra == 'all'
Requires-Dist: flake8-comprehensions ; extra == 'all'
Requires-Dist: flake8-mutable ; extra == 'all'
Requires-Dist: flake8-print ; extra == 'all'
Requires-Dist: isort ; extra == 'all'
Requires-Dist: mypy ; extra == 'all'
Requires-Dist: numpydoc ; extra == 'all'
Requires-Dist: pre-commit ; extra == 'all'
Requires-Dist: codespell ; extra == 'all'
Requires-Dist: pylint ; extra == 'all'
Requires-Dist: sphinx ; extra == 'all'
Requires-Dist: sphinx-automodapi ; extra == 'all'
Requires-Dist: sphinx-rtd-theme ; extra == 'all'
Requires-Dist: sphinxcontrib-mermaid ; extra == 'all'
Requires-Dist: jupyter-book ; extra == 'all'
Requires-Dist: docutils <0.18 ; extra == 'all'
Provides-Extra: docs
Requires-Dist: sphinx ; extra == 'docs'
Requires-Dist: sphinx-automodapi ; extra == 'docs'
Requires-Dist: sphinx-rtd-theme ; extra == 'docs'
Requires-Dist: sphinxcontrib-mermaid ; extra == 'docs'
Requires-Dist: jupyter-book ; extra == 'docs'
Requires-Dist: numpydoc ; extra == 'docs'
Requires-Dist: docutils <0.18 ; extra == 'docs'
Provides-Extra: lint
Requires-Dist: black ; extra == 'lint'
Requires-Dist: check-manifest ; extra == 'lint'
Requires-Dist: flake8 ; extra == 'lint'
Requires-Dist: flake8-builtins ; extra == 'lint'
Requires-Dist: flake8-comprehensions ; extra == 'lint'
Requires-Dist: flake8-mutable ; extra == 'lint'
Requires-Dist: flake8-print ; extra == 'lint'
Requires-Dist: isort ; extra == 'lint'
Requires-Dist: mypy ; extra == 'lint'
Requires-Dist: numpydoc ; extra == 'lint'
Requires-Dist: pre-commit ; extra == 'lint'
Requires-Dist: codespell ; extra == 'lint'
Requires-Dist: pylint ; extra == 'lint'
Provides-Extra: test
Requires-Dist: pytest ; extra == 'test'
Requires-Dist: pytest-cov ; extra == 'test'
Requires-Dist: pytest-flake8 ; extra == 'test'
Requires-Dist: pytest-xdist ; extra == 'test'
Requires-Dist: pytest-mock ; extra == 'test'
